{
  "title": "物理可行的世界模型：面向查询条件具身AI",
  "source_url": "https://arxiv.org/abs/2605.30542",
  "summary": "本文指出现有观测预测型世界模型在具身AI中会产生物理上错误的推演，因为不同物理系统可能视觉相同但干预结果不同。作者提出应构建基于查询条件的最简物理抽象模型，包含模块化组件和自主编排器，以生成可解释、可验证且符合干预结果的世界模型。",
  "tags": [
    "世界模型",
    "具身AI",
    "物理可行性",
    "干预查询",
    "模块化架构"
  ],
  "category": "paper",
  "status": "draft",
  "collected_at": "2026-06-01T17:45:08.147477+08:00",
  "published_at": null,
  "ai_analysis": {
    "relevance_score": 8,
    "key_points": [
      "现有世界模型因忽略潜在物理差异而推荐不可行动作",
      "提出查询条件的最简物理抽象作为设计原则",
      "模型包含环境表示、状态估计、动作规范等模块",
      "编排器动态组合组件以适配不同查询",
      "在现有系统失败的查询上展示有效性"
    ],
    "sentiment": "positive"
  },
  "id": "github-20260601-028",
  "source": "github_hackernews_arxiv_cs_ai"
}